{
  "fields": [
    {
      "fieldName": "numeroCartao",
      "fieldType": "Integer"
    },
    {
      "fieldName": "validadeCartao",
      "fieldType": "String"
    },
    {
      "fieldName": "codigoCartao",
      "fieldType": "Integer"
    }
  ],
  "relationships": [],
  "entityType": "user-task-form",
  "processBpmnId": "ProcessoIngresso",
  "processEntityName": "ProcessoIngresso",
  "taskBpmnId": "Pagamento",
  "domainEntityName": "Ingresso",
  "service": "serviceClass",
  "dto": "mapstruct",
  "jpaMetamodelFiltering": false,
  "readOnly": false,
  "pagination": "no",
  "name": "Pagamento",
  "changelogDate": "20210401000004",
  "skipFakeData": true
}
